LEGO_HQEC/__init__.py
LEGO_HQEC/DIstanceFind/DistanceFInder.py
LEGO_HQEC/DIstanceFind/InputProcessor.py
LEGO_HQEC/DIstanceFind/OperatorProcessor.py
LEGO_HQEC/OperatorPush/ExportToolbox.py
LEGO_HQEC/OperatorPush/NetworkToolbox.py
LEGO_HQEC/OperatorPush/OperatorToolbox.py
LEGO_HQEC/OperatorPush/PushingToolbox.py
LEGO_HQEC/OperatorPush/TensorToolbox.py
LEGO_HQEC/OperatorPush/HypertilingCompatibility/SRG_to_HTN.py
LEGO_HQEC/OperatorPush/Presets/HTN_vertex_inflation.py
LEGO_HQEC/OperatorPush/Presets/HaPPY_code.py
LEGO_HQEC/OperatorPush/Presets/Holographic_ReedMuller.py
LEGO_HQEC/OperatorPush/Presets/Holographic_Steane_code.py
LEGO_HQEC/OperatorPush/Presets/SCF.py
LEGO_HQEC/OperatorPush/Presets/SixOneThree.py
LEGO_HQEC/OperatorPush/Presets/happy_plus_RM.py
LEGO_HQEC/OperatorPush/Presets/happy_plus_steane.py
LEGO_HQEC/OperatorPush/Presets/sevenonethree.py
LEGO_HQEC/OperatorPush/Presets/steane_plus_RM.py
LEGO_HQEC/QuDec/ErasureDecoder.py
LEGO_HQEC/QuDec/InputProcessor.py
LEGO_HQEC/QuDec/Mod2Algebra.py
LEGO_HQEC/QuDec/OperatorProcessor.py
LEGO_HQEC/QuDec/OutputProcessor.py
LEGO_HQEC/QuDec/PauliDecoder.py
LEGO_HQEC/QuDec/TN_decoder.py
lego_hqec-0.1.1.dist-info/licenses/LICENSE.md
lego_hqec-0.1.1.dist-info/METADATA
lego_hqec-0.1.1.dist-info/WHEEL
lego_hqec-0.1.1.dist-info/top_level.txt
lego_hqec-0.1.1.dist-info/RECORD
