Metadata-Version: 2.4
Name: lego-hqec
Version: 0.1.1
Summary: A package for accelerating holographic quantum error-correcting codes research
Author-email: Junyu Fan <fzhjerry@gmail.com>, Matthew Steinberg <matt.steinberg3@gmail.com>
License-Expression: Apache-2.0
Project-URL: Homepage, https://github.com/QML-Group/HQEC
Project-URL: Repository, https://github.com/QML-Group/HQEC
Classifier: Programming Language :: Python :: 3
Classifier: Operating System :: OS Independent
Requires-Python: >=3.9
License-File: LICENSE.md
Requires-Dist: numpy>=1.21
Requires-Dist: gurobipy>=10.0
Requires-Dist: tensornetwork>=0.4
Requires-Dist: hypertiling>=1.2
Requires-Dist: psutil>=5.8
Requires-Dist: galois>=0.3
Dynamic: license-file
